vollseg/CARE.py
vollseg/CellPose.py
vollseg/MASKUNET.py
vollseg/OptimizeThreshold.py
vollseg/PredictTiledLoader.py
vollseg/Projection3D.py
vollseg/ProjectionUpsampling3D.py
vollseg/SimplePatches.py
vollseg/SmartNucleiPatches.py
vollseg/SmartPatches.py
vollseg/SmartSeeds2D.py
vollseg/SmartSeeds3D.py
vollseg/StarDist2D.py
vollseg/StarDist3D.py
vollseg/Tiles.py
vollseg/Tiles_3D.py
vollseg/TrainTiledLoader.py
vollseg/UNET.py
vollseg/__init__.py
vollseg/_version.py
vollseg/chunked_segmentation.py
vollseg/get_data.py
vollseg/inference.py
vollseg/inrimage.py
vollseg/label_utils.py
vollseg/matching.py
vollseg/nmslabel.py
vollseg/pretrained.py
vollseg/seedpool.py
vollseg/spatial_image.py
vollseg/unetstarmask.py
vollseg/utils.py
vollseg/_tests/__init__.py
vollseg-32.4.0.dist-info/licenses/LICENSE
vollseg-32.4.0.dist-info/METADATA
vollseg-32.4.0.dist-info/WHEEL
vollseg-32.4.0.dist-info/entry_points.txt
vollseg-32.4.0.dist-info/top_level.txt
vollseg-32.4.0.dist-info/RECORD
