Metadata-Version: 2.4
Name: vollseg
Version: 32.4.0
Summary: Segmentation tool for biological cells of irregular size and shape in 3D and 2D.
Home-page: https://github.com/Kapoorlabs-CAPED/vollseg
Author: Varun Kapoor,Claudia Carabana Garcia,Mari Tolonen,Jakub Sedzinski
Author-email: randomaccessiblekapoor@gmail.com
License: BSD-3-Clause
Project-URL: Bug Tracker, https://github.com/Kapoorlabs-CAPED/vollseg/issues
Project-URL: Documentation, https://github.com/Kapoorlabs-CAPED/vollseg#README.md
Project-URL: Source Code, https://github.com/Kapoorlabs-CAPED/vollseg
Project-URL: User Support, https://github.com/Kapoorlabs-CAPED/vollseg/issues
Classifier: Development Status :: 5 - Production/Stable
Classifier: Intended Audience :: Developers
Classifier: License :: OSI Approved :: BSD License
Classifier: Operating System :: OS Independent
Classifier: Programming Language :: Python
Classifier: Programming Language :: Python :: 3
Classifier: Programming Language :: Python :: 3 :: Only
Classifier: Programming Language :: Python :: 3.8
Classifier: Programming Language :: Python :: 3.9
Classifier: Programming Language :: Python :: 3.10
Classifier: Topic :: Scientific/Engineering :: Image Processing
Requires-Python: >=3.8
License-File: LICENSE
Requires-Dist: pandas
Requires-Dist: scipy
Requires-Dist: tifffile
Requires-Dist: matplotlib
Requires-Dist: napari
Requires-Dist: cellpose
Requires-Dist: torch
Requires-Dist: test_tube
Requires-Dist: lightning
Requires-Dist: pynvml
Requires-Dist: poetry
Requires-Dist: stardist
Provides-Extra: testing
Requires-Dist: tox; extra == "testing"
Requires-Dist: pytest; extra == "testing"
Requires-Dist: pytest-cov; extra == "testing"
Dynamic: license-file
